setup.py
threespace/__init__.py
threespace/threespace_api.py
threespace/threespace_utils.py
threespace/win32_threespace_utils.py
threespace.egg-info/PKG-INFO
threespace.egg-info/SOURCES.txt
threespace.egg-info/dependency_links.txt
threespace.egg-info/top_level.txt