Metadata-Version: 1.0
Name: threespace
Version: 2.0.1.0
Summary: Library for interfacing with the YEI 3-Space Sensor
Home-page: https://github.com/Knio/threespace
Author: Tom Flanagan
Author-email: tom@zkpq.ca
License: GPLv3
Platform: UNKNOWN
